2_Periodo/AC_I/EDS 1/GUIA_IX/Exercicio08/Exercicio8.v
// ---------------------------
// -- test clock generator (1)
// ---------------------------
module clock ( output clk );
reg clk;
initial
begin
clk = 1'b0;
end
always
begin
#12 clk = ~clk;
end
endmodule // clock ( )

module pulse( signal,clock );
input clock;
output signal;
reg
signal;
always@(clock)
begin
signal = 1'b1;
#2 signal = 1'b0;
#2 signal = 1'b1;
#2 signal = 1'b0;
end
endmodule // pulse

module Exercicio8;
wire clk;
wire signal;
clock CLK1 ( clk );
pulse PUL1(signal,clk);
initial begin
$dumpfile ( "Exercicio_8.vcd" );
$dumpvars;
#120 $finish;
end
endmodule // Exercicio8 ( )

2_Periodo/AC_I/EDS 1/GUIA_IX/Exercicio08/Exercicio_8.vcd
$date
	Sun Apr  8 21:21:31 2018
$end
$version
	Icarus Verilog
$end
$timescale
	1s
$end
$scope module Exercicio8 $end
$var wire 1 ! clk $end
$var wire 1 " signal $end
$scope module CLK1 $end
$var reg 1 # clk $end
$upscope $end
$scope module PUL1 $end
$var wire 1 ! clock $end
$var reg 1 $ signal $end
$upscope $end
$upscope $end
$enddefinitions $end
#0
$dumpvars
1$
0#
1"
0!
$end
#2
0$
0"
#4
1$
1"
#6
0$
0"
#12
1$
1"
1#
1!
#14
0$
0"
#16
1$
1"
#18
0$
0"
#24
1$
1"
0#
0!
#26
0$
0"
#28
1$
1"
#30
0$
0"
#36
1$
1"
1#
1!
#38
0$
0"
#40
1$
1"
#42
0$
0"
#48
1$
1"
0#
0!
#50
0$
0"
#52
1$
1"
#54
0$
0"
#60
1$
1"
1#
1!
#62
0$
0"
#64
1$
1"
#66
0$
0"
#72
1$
1"
0#
0!
#74
0$
0"
#76
1$
1"
#78
0$
0"
#84
1$
1"
1#
1!
#86
0$
0"
#88
1$
1"
#90
0$
0"
#96
1$
1"
0#
0!
#98
0$
0"
#100
1$
1"
#102
0$
0"
#108
1$
1"
1#
1!
#110
0$
0"
#112
1$
1"
#114
0$
0"
#120
1$
1"
0#
0!
