2_Periodo/AC_I/EDS 1/GUIA_IX/Exercicio07/Exercicio7.v
// ---------------------------
// -- test clock generator (1)
// ---------------------------
module clock ( output clk );
reg clk;
initial
begin
clk = 1'b0;
end
always
begin
#12 clk = ~clk;
end
endmodule // clock ( )

module pulse( signal,clock );
input clock;
output signal;
reg
signal;
always@(negedge clock)
begin
signal = 1'b1;
#2 signal = 1'b0;
#2 signal = 1'b1;
#2 signal = 1'b0;
end
endmodule // pulse

module Exercicio7;
wire clk;
wire signal;
clock CLK1 (clk);
pulse PULS1(signal,clk);
initial begin
$dumpfile ( "Exercicio_7.vcd" );
$dumpvars;
#120 $finish;
end
endmodule // Exercicio7 ( )

2_Periodo/AC_I/EDS 1/GUIA_IX/Exercicio07/Exercicio_7.vcd
$date
	Sun Apr  8 21:17:09 2018
$end
$version
	Icarus Verilog
$end
$timescale
	1s
$end
$scope module Exercicio7 $end
$var wire 1 ! clk $end
$var wire 1 " signal $end
$scope module CLK1 $end
$var reg 1 # clk $end
$upscope $end
$scope module PULS1 $end
$var wire 1 ! clock $end
$var reg 1 $ signal $end
$upscope $end
$upscope $end
$enddefinitions $end
#0
$dumpvars
x$
0#
x"
0!
$end
#12
1#
1!
#24
1$
1"
0#
0!
#26
0$
0"
#28
1$
1"
#30
0$
0"
#36
1#
1!
#48
1$
1"
0#
0!
#50
0$
0"
#52
1$
1"
#54
0$
0"
#60
1#
1!
#72
1$
1"
0#
0!
#74
0$
0"
#76
1$
1"
#78
0$
0"
#84
1#
1!
#96
1$
1"
0#
0!
#98
0$
0"
#100
1$
1"
#102
0$
0"
#108
1#
1!
#120
1$
1"
0#
0!
